{"key":"city-0139-黑龙江省-牡丹江市","province":"黑龙江省","city":"牡丹江市","count":10,"fields":["id","name","religion","faction","province","city","county","address","fullAddress","regionCode","latitude","longitude"],"places":[["1171733691538341888","海林市老道庙","道教","全真","黑龙江省","牡丹江市","海林市","黑龙江省牡丹江市海林市二道河子镇","黑龙江省牡丹江市海林市二道河子镇","AREA-101081008",null,null],["1171734030031257600","报恩寺","佛教","汉语系","黑龙江省","牡丹江市","海林市","黑龙江省牡丹江市海林市子荣街","黑龙江省牡丹江市海林市子荣街","AREA-101081008",null,null],["1171734030282915840","大光明寺","佛教","汉语系","黑龙江省","牡丹江市","绥芬河市","黑龙江省绥芬河市乌苏里大街","黑龙江省绥芬河市乌苏里大街","AREA-101081007",null,null],["1171734030115143680","回云寺","佛教","汉语系","黑龙江省","牡丹江市","林口县","黑龙江省牡丹江市林口县龙爪镇高云村","黑龙江省牡丹江市林口县龙爪镇高云村","AREA-101081006",null,null],["1171734029951565824","金光寺","佛教","汉语系","黑龙江省","牡丹江市","东宁县","黑龙江省牡丹江市东宁县东宁镇西岭村","黑龙江省牡丹江市东宁县东宁镇西岭村","AREA-101081005",null,null],["1171734030635237377","九层寺","佛教","汉语系","黑龙江省","牡丹江市","阳明区","黑龙江省牡丹江市阳明区五林镇亮子河水库","黑龙江省牡丹江市阳明区五林镇亮子河水库","AREA-101081002",null,null],["1171734030199029761","莲花寺","佛教","汉语系","黑龙江省","牡丹江市","林口县","黑龙江省牡丹江市林口县莲花镇莲花村","黑龙江省牡丹江市林口县莲花镇莲花村","AREA-101081006",null,null],["1171734030199029762","通觉寺","佛教","汉语系","黑龙江省","牡丹江市","穆棱市","黑龙江省牡丹江市穆棱市河西乡","黑龙江省牡丹江市穆棱市河西乡","AREA-101081010",null,null],["1171734030199029760","兴隆寺","佛教","汉语系","黑龙江省","牡丹江市","林口县","黑龙江省牡丹江市林口县林口镇杨木岗","黑龙江省牡丹江市林口县林口镇杨木岗","AREA-101081006",null,null],["1171734029867679744","圆通讲寺","佛教","汉语系","黑龙江省","牡丹江市","爱民区","黑龙江省牡丹江市爱民区北山街","黑龙江省牡丹江市爱民区北山街","AREA-101081003",null,null]]}