{"key":"city-0292-陕西省-西安市","province":"陕西省","city":"西安市","count":166,"fields":["id","name","religion","faction","province","city","county","address","fullAddress","regionCode","latitude","longitude"],"places":[["1171733611519410176","安乐宫","道教","全真","陕西省","西安市","周至县","陕西省西安市周至县翠峰镇农林村","陕西省西安市周至县翠峰镇农林村","AREA-101270111",null,null],["1171733611183865856","碧天洞道观","道教","全真","陕西省","西安市","蓝田县","陕西省西安市蓝田县蓝桥镇","陕西省西安市蓝田县蓝桥镇","AREA-101270110",null,null],["1171733611519410179","财神庙","道教","全真","陕西省","西安市","周至县","陕西省西安市周至县集贤镇赵代村","陕西省西安市周至县集贤镇赵代村","AREA-101270111",null,null],["1171733611347443713","朝元阁道观","道教","全真","陕西省","西安市","临潼区","陕西省西安市临潼区骊山街办东安村老母殿组","陕西省西安市临潼区骊山街办东安村老母殿组","AREA-101270108",null,null],["1171733611011899395","大重阳万寿宫","道教","全真","陕西省","西安市","户县","陕西省西安市户县祖庵镇北街村","陕西省西安市户县祖庵镇北街村","AREA-101270112",null,null],["1171733611519410182","丹阳观","道教","全真","陕西省","西安市","周至县","陕西省西安市周至县竹峪镇丹阳村","陕西省西安市周至县竹峪镇丹阳村","AREA-101270111",null,null],["1171733611007705090","东岳庙","道教","全真","陕西省","西安市","长安区","陕西省西安市长安区鸣犊镇咀头村","陕西省西安市长安区鸣犊镇咀头村","AREA-101270109",null,null],["1171733611007705088","斗母宫","道教","全真","陕西省","西安市","长安区","陕西省西安市长安区杨庄太兴山","陕西省西安市长安区杨庄太兴山","AREA-101270109",null,null],["1171733611091591170","关帝庙","道教","全真","陕西省","西安市","户县","陕西省西安市户县西街村","陕西省西安市户县西街村","AREA-101270112",null,null],["1171733611519410178","关帝庙","道教","全真","陕西省","西安市","周至县","陕西省西安市周至县集贤镇严家堡村","陕西省西安市周至县集贤镇严家堡村","AREA-101270111",null,null],["1171733611091591171","集仙观","道教","全真","陕西省","西安市","户县","陕西省西安市户县蒋村镇甘峪口村","陕西省西安市户县蒋村镇甘峪口村","AREA-101270112",null,null],["1171733610923819009","金仙观","道教","全真","陕西省","西安市","长安区","陕西省西安市长安区子午街道子午峪","陕西省西安市长安区子午街道子午峪","AREA-101270109",null,null],["1171733611347443712","老母宫","道教","全真","陕西省","西安市","临潼区","陕西省西安市临潼区骊山风景区","陕西省西安市临潼区骊山风景区","AREA-101270108",null,null],["1171733611431329792","楼观台道观","道教","全真","陕西省","西安市","周至县","陕西省西安市周至县楼观镇东楼村","陕西省西安市周至县楼观镇东楼村","AREA-101270111",null,null],["1171733611267751936","明圣宫","道教","全真","陕西省","西安市","临潼区","陕西省西安市临潼区骊山街办东安村老母殿组","陕西省西安市临潼区骊山街办东安村老母殿组","AREA-101270108",null,null],["1171733611011899392","磨针观","道教","全真","陕西省","西安市","长安区","陕西省西安市长安区杨庄乡太兴山","陕西省西安市长安区杨庄乡太兴山","AREA-101270109",null,null],["1171733611347443715","青华宫","道教","全真","陕西省","西安市","雁塔区","陕西省西安市雁塔区曲江春临村","陕西省西安市雁塔区曲江春临村","AREA-101270106",null,null],["1171733611519410181","青牛庵","道教","全真","陕西省","西安市","周至县","陕西省西安市周至县翠峰镇丁家凹村","陕西省西安市周至县翠峰镇丁家凹村","AREA-101270111",null,null],["1171733611091591172","清凉山道观","道教","全真","陕西省","西安市","户县","陕西省西安市户县蒋村镇富村窑村","陕西省西安市户县蒋村镇富村窑村","AREA-101270112",null,null],["1171733611347443714","人祖庙","道教","全真","陕西省","西安市","临潼区","陕西省西安市临潼区仁宗街办仁宗村","陕西省西安市临潼区仁宗街办仁宗村","AREA-101270108",null,null],["1171733611011899394","圣母宫","道教","全真","陕西省","西安市","长安区","陕西省西安市长安区滦镇黑沟","陕西省西安市长安区滦镇黑沟","AREA-101270109",null,null],["1171733610760241152","太白庙","道教","全真","陕西省","西安市","灞桥区","陕西省西安市灞桥区新筑街办龙王庙村","陕西省西安市灞桥区新筑街办龙王庙村","AREA-101270104",null,null],["1171733611183865857","西安市都城隍庙","道教","全真","陕西省","西安市","莲湖区","陕西省西安市莲湖区西大街129号","陕西省西安市莲湖区西大街129号","AREA-101270103",null,null],["1171733610839932928","西安市万寿八仙宫","道教","全真","陕西省","西安市","碑林区","陕西省西安市碑林区东关北火巷12号","陕西省西安市碑林区东关北火巷12号","AREA-101270102",null,null],["1171733611519410183","仙姑宫","道教","全真","陕西省","西安市","周至县","陕西省西安市周至县翠峰乡农林村","陕西省西安市周至县翠峰乡农林村","AREA-101270111",null,null],["1171733610923819008","湘子庙","道教","全真","陕西省","西安市","碑林区","陕西省西安市碑林区湘子庙1号","陕西省西安市碑林区湘子庙1号","AREA-101270102",null,null],["1171733611519410180","药王宫","道教","全真","陕西省","西安市","周至县","陕西省西安市周至县楼观镇东楼村","陕西省西安市周至县楼观镇东楼村","AREA-101270111",null,null],["1171733611091591169","玉蝉台道观","道教","全真","陕西省","西安市","户县","陕西省西安市户县玉蝉台曲抱村","陕西省西安市户县玉蝉台曲抱村","AREA-101270112",null,null],["1171733611011899393","玉皇楼道观","道教","全真","陕西省","西安市","长安区","陕西省西安市长安区子午街道小五台","陕西省西安市长安区子午街道小五台","AREA-101270109",null,null],["1171733611099979777","真武庙道观","道教","全真","陕西省","西安市","蓝田县","陕西省西安市蓝田县史家寨柿园村","陕西省西安市蓝田县史家寨柿园村","AREA-101270110",null,null],["1171733611091591168","重阳成道宫","道教","全真","陕西省","西安市","户县","陕西省西安市户县祖庵镇成道宫村","陕西省西安市户县祖庵镇成道宫村","AREA-101270112",null,null],["1171733600140263435","白龙寺","佛教","汉语系","陕西省","西安市","户县","陕西省西安市户县蒋村镇白龙村","陕西省西安市户县蒋村镇白龙村","AREA-101270112",null,null],["1171733600136069122","白马寺","佛教","汉语系","陕西省","西安市","户县","陕西省西安市户县秦渡镇北庞村","陕西省西安市户县秦渡镇北庞村","AREA-101270112",null,null],["1171733600140263430","白云寺","佛教","汉语系","陕西省","西安市","户县","陕西省西安市户县秦渡镇秦六村","陕西省西安市户县秦渡镇秦六村","AREA-101270112",null,null],["1171733599586615298","百塔寺","佛教","汉语系","陕西省","西安市","长安区","陕西省西安市长安区子午街道天子口村","陕西省西安市长安区子午街道天子口村","AREA-101270109",null,null],["1171733599586615309","宝庵寺","佛教","汉语系","陕西省","西安市","长安区","陕西省西安市长安区引镇街道高村","陕西省西安市长安区引镇街道高村","AREA-101270109",null,null],["1171733600140263438","宝林寺","佛教","汉语系","陕西省","西安市","户县","陕西省西安市户县景区管理局紫阁峪紫阁村","陕西省西安市户县景区管理局紫阁峪紫阁村","AREA-101270112",null,null],["1171733600140263424","宝泉寺","佛教","汉语系","陕西省","西安市","户县","陕西省西安市户县石井镇潭峪口村","陕西省西安市户县石井镇潭峪口村","AREA-101270112",null,null],["1171733600047988737","草堂寺","佛教","汉语系","陕西省","西安市","户县","陕西省西安市户县草堂镇草堂营村","陕西省西安市户县草堂镇草堂营村","AREA-101270112",null,null],["1171733599083298818","禅经寺","佛教","汉语系","陕西省","西安市","长安区","陕西省西安市长安区杜曲镇小江村","陕西省西安市长安区杜曲镇小江村","AREA-101270109",null,null],["1171733598911332353","成就寺","佛教","汉语系","陕西省","西安市","灞桥区","陕西省西安市灞桥区红旗街办向阳沟村","陕西省西安市灞桥区红旗街办向阳沟村","AREA-101270104",null,null],["1171733600136069126","崇圣讲寺","佛教","汉语系","陕西省","西安市","户县","陕西省西安市户县庞光镇孙姑村","陕西省西安市户县庞光镇孙姑村","AREA-101270112",null,null],["1171733599083298821","慈云寺","佛教","汉语系","陕西省","西安市","长安区","陕西省西安市长安区太乙街道上寨村","陕西省西安市长安区太乙街道上寨村","AREA-101270109",null,null],["1171733598823251970","大阿弥陀寺","佛教","汉语系","陕西省","西安市","灞桥区","陕西省西安市灞桥区席王街办杨疙瘩村","陕西省西安市灞桥区席王街办杨疙瘩村","AREA-101270104",null,null],["1171733600131874818","大慈悲寺","佛教","汉语系","陕西省","西安市","户县","陕西省西安市户县石井镇上庄村","陕西省西安市户县石井镇上庄村","AREA-101270112",null,null],["1171733600559693824","大慈恩寺","佛教","汉语系","陕西省","西安市","雁塔区","陕西省西安市雁塔区慈恩路1号","陕西省西安市雁塔区慈恩路1号","AREA-101270106",null,null],["1171733601222393859","大秦寺","佛教","汉语系","陕西省","西安市","周至县","陕西省西安市周至县楼观镇塔峪村","陕西省西安市周至县楼观镇塔峪村","AREA-101270111",null,null],["1171733600140263434","大唐兴圣寺","佛教","汉语系","陕西省","西安市","户县","陕西省西安市户县庞光镇乌东村","陕西省西安市户县庞光镇乌东村","AREA-101270112",null,null],["1171733600643579904","大兴善寺","佛教","汉语系","陕西省","西安市","雁塔区","陕西省西安市雁塔区兴善寺西街55号","陕西省西安市雁塔区兴善寺西街55号","AREA-101270106",null,null],["1171733600131874816","大圆寺","佛教","汉语系","陕西省","西安市","户县","陕西省西安市户县草堂镇杜家庄","陕西省西安市户县草堂镇杜家庄","AREA-101270112",null,null],["1171733599586615310","道安寺","佛教","汉语系","陕西省","西安市","长安区","陕西省西安市长安区杜曲镇彰仪村","陕西省西安市长安区杜曲镇彰仪村","AREA-101270109",null,null],["1171733599754387461","东禅观音寺","佛教","汉语系","陕西省","西安市","长安区","陕西省西安市长安区终南山嘉午台","陕西省西安市长安区终南山嘉午台","AREA-101270109",null,null],["1171733600312229888","二天门寺","佛教","汉语系","陕西省","西安市","临潼区","陕西省西安市临潼区骊山街办寺沟村","陕西省西安市临潼区骊山街办寺沟村","AREA-101270108",null,null],["1171733600140263427","法幢寺","佛教","汉语系","陕西省","西安市","户县","陕西省西安市户县苍游镇李柏村","陕西省西安市户县苍游镇李柏村","AREA-101270112",null,null],["1171733600043794434","法海寺","佛教","汉语系","陕西省","西安市","沣东新城","陕西省西咸新区沣东新城王寺街办周吴村","陕西省西咸新区沣东新城王寺街办周吴村","AREA-101270114",null,null],["1171733599083298820","法华讲寺","佛教","汉语系","陕西省","西安市","长安区","陕西省西安市长安区滦镇街街办玉皇坪村","陕西省西安市长安区滦镇街街办玉皇坪村","AREA-101270109",null,null],["1171733599083298816","法华寺","佛教","汉语系","陕西省","西安市","长安区","陕西省西安市长安区滦镇街道观音山","陕西省西安市长安区滦镇街道观音山","AREA-101270109",null,null],["1171733599079104512","法音寺","佛教","汉语系","陕西省","西安市","长安区","陕西省西安市长安区鸣犊镇鸣犊镇村","陕西省西安市长安区鸣犊镇鸣犊镇村","AREA-101270109",null,null],["1171733600136069128","非相禅寺","佛教","汉语系","陕西省","西安市","户县","陕西省西安市户县石井镇石西村","陕西省西安市户县石井镇石西村","AREA-101270112",null,null],["1171733599586615301","丰德寺","佛教","汉语系","陕西省","西安市","长安区","陕西省西安市长安区滦镇街道沣峪口村","陕西省西安市长安区滦镇街道沣峪口村","AREA-101270109",null,null],["1171733600140263440","佛山寺","佛教","汉语系","陕西省","西安市","蓝田县","陕西省西安市蓝田县汤峪镇","陕西省西安市蓝田县汤峪镇","AREA-101270110",null,null],["1171733600136069120","福慧庵","佛教","汉语系","陕西省","西安市","户县","陕西省西安市户县庞光镇化东村","陕西省西安市户县庞光镇化东村","AREA-101270112",null,null],["1171733599079104520","甘霖寺","佛教","汉语系","陕西省","西安市","长安区","陕西省西安市长安区韦曲街道皇子坡","陕西省西安市长安区韦曲街道皇子坡","AREA-101270109",null,null],["1171733599079104517","古观音禅寺","佛教","汉语系","陕西省","西安市","长安区","陕西省西安市长安区东大街道罗汉洞村","陕西省西安市长安区东大街道罗汉洞村","AREA-101270109",null,null],["1171733599590809603","观音禅院","佛教","汉语系","陕西省","西安市","长安区","陕西省西安市长安区滦镇街道二道桥","陕西省西安市长安区滦镇街道二道桥","AREA-101270109",null,null],["1171733599074910209","观音寺","佛教","汉语系","陕西省","西安市","长安区","陕西省西安市长安区杜曲镇南樊村","陕西省西安市长安区杜曲镇南樊村","AREA-101270109",null,null],["1171733665646903298","广仁寺","佛教","藏语系","陕西省","西安市","莲湖区","陕西省西安市莲湖区西北一路152号","陕西省西安市莲湖区西北一路152号","AREA-101270103",null,null],["1171733599754387463","归元寺","佛教","汉语系","陕西省","西安市","沣东新城","陕西省西咸新区沣东新城王寺街道办事处五一村","陕西省西咸新区沣东新城王寺街道办事处五一村","AREA-101270114",null,null],["1171733599590809601","圭峰寺","佛教","汉语系","陕西省","西安市","长安区","陕西省西安市长安区东大街道圭峰山","陕西省西安市长安区东大街道圭峰山","AREA-101270109",null,null],["1171733601222393862","海藏寺","佛教","汉语系","陕西省","西安市","周至县","陕西省西安市周至县哑柏镇联星村","陕西省西安市周至县哑柏镇联星村","AREA-101270111",null,null],["1171733599083298827","海莲寺","佛教","汉语系","陕西省","西安市","长安区","陕西省西安市长安区韦曲街道双磨村","陕西省西安市长安区韦曲街道双磨村","AREA-101270109",null,null],["1171733600396115968","红鹤寺","佛教","汉语系","陕西省","西安市","临潼区","陕西省西安市临潼区斜口街办军王岭村","陕西省西安市临潼区斜口街办军王岭村","AREA-101270108",null,null],["1171733599074910210","红云寺","佛教","汉语系","陕西省","西安市","长安区","陕西省西安市长安区杨庄乡石佛庄","陕西省西安市长安区杨庄乡石佛庄","AREA-101270109",null,null],["1171733599754387462","宏福寺","佛教","汉语系","陕西省","西安市","长安区","陕西省西安市长安区杜曲镇西樊村","陕西省西安市长安区杜曲镇西樊村","AREA-101270109",null,null],["1171733600047988736","洪觉古寺","佛教","汉语系","陕西省","西安市","沣东新城","陕西省西咸新区沣东新城斗门街办堰下张村","陕西省西咸新区沣东新城斗门街办堰下张村","AREA-101270114",null,null],["1171733600039600128","花光寺","佛教","汉语系","陕西省","西安市","沣东新城","陕西省西安市长安区王寺街道","陕西省西安市长安区王寺街道","AREA-101270114",null,null],["1171733599079104516","华严寺","佛教","汉语系","陕西省","西安市","长安区","陕西省西安市长安区韦曲街道四府村","陕西省西安市长安区韦曲街道四府村","AREA-101270109",null,null],["1171733598911332352","慧静寺","佛教","汉语系","陕西省","西安市","灞桥区","陕西省西安市灞桥区东城大道西段","陕西省西安市灞桥区东城大道西段","AREA-101270104",null,null],["1171733599079104513","极乐庵","佛教","汉语系","陕西省","西安市","长安区","陕西省西安市长安区太乙宫街道黑沟","陕西省西安市长安区太乙宫街道黑沟","AREA-101270109",null,null],["1171733600136069134","极乐寺","佛教","汉语系","陕西省","西安市","户县","陕西省西安市户县石井镇栗园坡村","陕西省西安市户县石井镇栗园坡村","AREA-101270112",null,null],["1171733600396115970","极乐寺","佛教","汉语系","陕西省","西安市","未央区","陕西省西安市未央区辛家庙街道新房村","陕西省西安市未央区辛家庙街道新房村","AREA-101270105",null,null],["1171733600136069135","金峰寺","佛教","汉语系","陕西省","西安市","户县","陕西省西安市户县庞光镇化丰村","陕西省西安市户县庞光镇化丰村","AREA-101270112",null,null],["1171733600039600129","金佛寺","佛教","汉语系","陕西省","西安市","沣东新城","陕西省西咸新区沣东新城斗门街道先锋村","陕西省西咸新区沣东新城斗门街道先锋村","AREA-101270114",null,null],["1171733599079104514","净居寺","佛教","汉语系","陕西省","西安市","长安区","陕西省西安市长安区滦镇街道东佛沟","陕西省西安市长安区滦镇街道东佛沟","AREA-101270109",null,null],["1171733600136069132","净居寺","佛教","汉语系","陕西省","西安市","户县","陕西省西安市户县石井镇土门村","陕西省西安市户县石井镇土门村","AREA-101270112",null,null],["1171733600136069129","净如寺","佛教","汉语系","陕西省","西安市","户县","陕西省西安市户县庞光镇焦东村","陕西省西安市户县庞光镇焦东村","AREA-101270112",null,null],["1171733599074910208","净土茅蓬寺","佛教","汉语系","陕西省","西安市","长安区","陕西省西安市长安区五台乡南五台","陕西省西安市长安区五台乡南五台","AREA-101270109",null,null],["1171733599586615299","净业寺","佛教","汉语系","陕西省","西安市","长安区","陕西省西安市长安区滦镇街道后岸山","陕西省西安市长安区滦镇街道后岸山","AREA-101270109",null,null],["1171733600131874821","鸠摩罗什寺","佛教","汉语系","陕西省","西安市","户县","陕西省西安市户县余下镇罗什村","陕西省西安市户县余下镇罗什村","AREA-101270112",null,null],["1171733599586615308","救苦寺","佛教","汉语系","陕西省","西安市","长安区","陕西省西安市长安区魏寨乡常沟村","陕西省西安市长安区魏寨乡常沟村","AREA-101270109",null,null],["1171733601222393857","聚贤寺","佛教","汉语系","陕西省","西安市","周至县","陕西省西安市周至县哑柏镇坡典村","陕西省西安市周至县哑柏镇坡典村","AREA-101270111",null,null],["1171733600140263432","雷音寺","佛教","汉语系","陕西省","西安市","户县","陕西省西安市户县石井镇站马村","陕西省西安市户县石井镇站马村","AREA-101270112",null,null],["1171733600136069138","冷泉寺","佛教","汉语系","陕西省","西安市","户县","陕西省西安市户县余下镇双庄村","陕西省西安市户县余下镇双庄村","AREA-101270112",null,null],["1171733599590809605","莲池寺","佛教","汉语系","陕西省","西安市","长安区","陕西省西安市长安区子午街道天子口村","陕西省西安市长安区子午街道天子口村","AREA-101270109",null,null],["1171733601222393864","莲花寺","佛教","汉语系","陕西省","西安市","周至县","陕西省西安市周至县九峰镇星峰村","陕西省西安市周至县九峰镇星峰村","AREA-101270111",null,null],["1171733600136069127","莲宗庵","佛教","汉语系","陕西省","西安市","户县","陕西省西安市户县余下镇南索村","陕西省西安市户县余下镇南索村","AREA-101270112",null,null],["1171733599586615307","亮碑寺","佛教","汉语系","陕西省","西安市","长安区","陕西省西安市长安区鸣犊镇马嘶坡村","陕西省西安市长安区鸣犊镇马嘶坡村","AREA-101270109",null,null],["1171733600140263431","灵音寺","佛教","汉语系","陕西省","西安市","户县","陕西省西安市户县甘亭镇小丰村","陕西省西安市户县甘亭镇小丰村","AREA-101270112",null,null],["1171733599754387459","灵应寺","佛教","汉语系","陕西省","西安市","长安区","陕西省西安市长安区东大街办东大村陵园东","陕西省西安市长安区东大街办东大村陵园东","AREA-101270109",null,null],["1171733599079104521","龙泉寺","佛教","汉语系","陕西省","西安市","长安区","陕西省西安市长安区王莽乡王家村","陕西省西安市长安区王莽乡王家村","AREA-101270109",null,null],["1171733600131874820","龙泉寺","佛教","汉语系","陕西省","西安市","户县","陕西省西安市户县天桥镇西涝峪口村","陕西省西安市户县天桥镇西涝峪口村","AREA-101270112",null,null],["1171733601222393861","龙泉寺","佛教","汉语系","陕西省","西安市","周至县","陕西省西安市周至县司竹镇龙泉寺","陕西省西安市周至县司竹镇龙泉寺","AREA-101270111",null,null],["1171733599234293760","弥陀寺","佛教","汉语系","陕西省","西安市","长安区","陕西省西安市长安区五台乡星火村","陕西省西安市长安区五台乡星火村","AREA-101270109",null,null],["1171733600136069137","弥陀寺","佛教","汉语系","陕西省","西安市","户县","陕西省西安市户县石井镇阿姑泉村","陕西省西安市户县石井镇阿姑泉村","AREA-101270112",null,null],["1171733599590809602","密严寺","佛教","汉语系","陕西省","西安市","长安区","陕西省西安市长安区滦镇街道上王村","陕西省西安市长安区滦镇街道上王村","AREA-101270109",null,null],["1171733599590809600","摩诃慈恩寺","佛教","汉语系","陕西省","西安市","长安区","陕西省西安市长安区杨庄乡太兴山","陕西省西安市长安区杨庄乡太兴山","AREA-101270109",null,null],["1171733599754387457","南峰禅寺","佛教","汉语系","陕西省","西安市","长安区","陕西省西安市长安区子午街道小五台","陕西省西安市长安区子午街道小五台","AREA-101270109",null,null],["1171733599590809604","牛角寺","佛教","汉语系","陕西省","西安市","长安区","陕西省西安市长安区子午街道子子午村","陕西省西安市长安区子午街道子子午村","AREA-101270109",null,null],["1171733599083298826","牛头禅寺","佛教","汉语系","陕西省","西安市","长安区","陕西省西安市长安区韦曲街道双竹村","陕西省西安市长安区韦曲街道双竹村","AREA-101270109",null,null],["1171733601054621696","暖泉寺","佛教","汉语系","陕西省","西安市","周至县","陕西省西安市周至县骆峪镇田家梁村","陕西省西安市周至县骆峪镇田家梁村","AREA-101270111",null,null],["1171733599586615304","平等寺","佛教","汉语系","陕西省","西安市","长安区","陕西省西安市长安区灵沼乡阿底村","陕西省西安市长安区灵沼乡阿底村","AREA-101270109",null,null],["1171733600136069136","菩萨寺","佛教","汉语系","陕西省","西安市","户县","陕西省西安市户县庞光镇华丰村","陕西省西安市户县庞光镇华丰村","AREA-101270112",null,null],["1171733599079104522","菩提寺","佛教","汉语系","陕西省","西安市","长安区","陕西省西安市长安区细柳镇蒲阳村","陕西省西安市长安区细柳镇蒲阳村","AREA-101270109",null,null],["1171733600140263433","菩提寺","佛教","汉语系","陕西省","西安市","户县","陕西省西安市户县大王镇大王西村","陕西省西安市户县大王镇大王西村","AREA-101270112",null,null],["1171733600136069131","普光明寺","佛教","汉语系","陕西省","西安市","户县","陕西省西安市户县余下镇沈家营村","陕西省西安市户县余下镇沈家营村","AREA-101270112",null,null],["1171733599754387460","普济寺","佛教","汉语系","陕西省","西安市","长安区","陕西省西安市长安区王曲街办满江红村","陕西省西安市长安区王曲街办满江红村","AREA-101270109",null,null],["1171733600643579905","青龙寺","佛教","汉语系","陕西省","西安市","雁塔区","陕西省西安市雁塔区西影路铁炉庙村","陕西省西安市雁塔区西影路铁炉庙村","AREA-101270106",null,null],["1171733598995218433","青音寺","佛教","汉语系","陕西省","西安市","长安区","陕西省西安市长安区五台乡大瓢村","陕西省西安市长安区五台乡大瓢村","AREA-101270109",null,null],["1171733598911332355","青云寺","佛教","汉语系","陕西省","西安市","灞桥区","陕西省西安市灞桥区红旗街办马家沟村","陕西省西安市灞桥区红旗街办马家沟村","AREA-101270104",null,null],["1171733599586615303","清净寺","佛教","汉语系","陕西省","西安市","长安区","陕西省西安市长安区滦镇街道摩天岭","陕西省西安市长安区滦镇街道摩天岭","AREA-101270109",null,null],["1171733599083298825","清凉寺","佛教","汉语系","陕西省","西安市","长安区","陕西省西安市长安区韦曲街道塔坡村","陕西省西安市长安区韦曲街道塔坡村","AREA-101270109",null,null],["1171733600727465985","清凉寺","佛教","汉语系","陕西省","西安市","周至县","陕西省西安市周至县广济镇曹家滩村","陕西省西安市周至县广济镇曹家滩村","AREA-101270111",null,null],["1171733600643579906","瑞光寺","佛教","汉语系","陕西省","西安市","周至县","陕西省西安市周至县二曲镇镇丰村","陕西省西安市周至县二曲镇镇丰村","AREA-101270111",null,null],["1171733599083298817","上天池寺","佛教","汉语系","陕西省","西安市","长安区","陕西省西安市长安区五台街办","陕西省西安市长安区五台街办","AREA-101270109",null,null],["1171733600224149504","上悟真寺","佛教","汉语系","陕西省","西安市","蓝田县","陕西省西安市蓝田县普化镇河湾口村","陕西省西安市蓝田县普化镇河湾口村","AREA-101270110",null,null],["1171733599586615296","圣寿寺","佛教","汉语系","陕西省","西安市","长安区","陕西省西安市长安区五台乡南五台","陕西省西安市长安区五台乡南五台","AREA-101270109",null,null],["1171733600131874817","胜光寺","佛教","汉语系","陕西省","西安市","户县","陕西省西安市户县苍游镇什王村","陕西省西安市户县苍游镇什王村","AREA-101270112",null,null],["1171733600043794433","石佛寺","佛教","汉语系","陕西省","西安市","沣东新城","陕西省西咸新区沣东新城斗门街办新庄村北","陕西省西咸新区沣东新城斗门街办新庄村北","AREA-101270114",null,null],["1171733600136069133","石井白云寺","佛教","汉语系","陕西省","西安市","户县","陕西省西安市户县石井镇白云村","陕西省西安市户县石井镇白云村","AREA-101270112",null,null],["1171733600136069121","石龙寺","佛教","汉语系","陕西省","西安市","户县","陕西省西安市户县蒋村镇曹村","陕西省西安市户县蒋村镇曹村","AREA-101270112",null,null],["1171733600136069124","石门寺","佛教","汉语系","陕西省","西安市","户县","陕西省西安市户县庞光镇化中村","陕西省西安市户县庞光镇化中村","AREA-101270112",null,null],["1171733600140263439","太平寺","佛教","汉语系","陕西省","西安市","户县","陕西省西安市户县景区管理局家福堂村冉家湾组","陕西省西安市户县景区管理局家福堂村冉家湾组","AREA-101270112",null,null],["1171733599586615305","天池寺","佛教","汉语系","陕西省","西安市","长安区","陕西省西安市长安区太乙宫街办蛟峪口村","陕西省西安市长安区太乙宫街办蛟峪口村","AREA-101270109",null,null],["1171733601222393858","天台寺","佛教","汉语系","陕西省","西安市","周至县","陕西省西安市周至县哑柏镇昌东村","陕西省西安市周至县哑柏镇昌东村","AREA-101270111",null,null],["1171733598995218432","罔极寺","佛教","汉语系","陕西省","西安市","碑林区","陕西省西安市碑林区东关炮房街49号","陕西省西安市碑林区东关炮房街49号","AREA-101270102",null,null],["1171733601222393863","文殊寺","佛教","汉语系","陕西省","西安市","周至县","陕西省西安市周至县终南镇高庙村","陕西省西安市周至县终南镇高庙村","AREA-101270111",null,null],["1171733598911332356","卧龙禅寺","佛教","汉语系","陕西省","西安市","碑林区","陕西省西安市碑林区柏树林街开通巷1号","陕西省西安市碑林区柏树林街开通巷1号","AREA-101270102",null,null],["1171733600136069125","西明寺","佛教","汉语系","陕西省","西安市","户县","陕西省西安市户县庞光镇炉西村","陕西省西安市户县庞光镇炉西村","AREA-101270112",null,null],["1171733600035405824","西山寺","佛教","汉语系","陕西省","西安市","沣东新城","陕西省西安市长安区王寺街道办纪杨乡黄堆村与七渠村之间","陕西省西安市长安区王寺街道办纪杨乡黄堆村与七渠村之间","AREA-101270114",null,null],["1171733599586615300","洗心茅蓬寺","佛教","汉语系","陕西省","西安市","长安区","陕西省西安市长安区滦镇街道白石峪","陕西省西安市长安区滦镇街道白石峪","AREA-101270109",null,null],["1171733600224149505","下悟真寺","佛教","汉语系","陕西省","西安市","蓝田县","陕西省西安市蓝田县普化镇","陕西省西安市蓝田县普化镇","AREA-101270110",null,null],["1171733600727465984","仙游寺","佛教","汉语系","陕西省","西安市","周至县","陕西省西安市周至县马召镇金盆村","陕西省西安市周至县马召镇金盆村","AREA-101270111",null,null],["1171733599083298824","香积寺","佛教","汉语系","陕西省","西安市","长安区","陕西省西安市长安区郭杜镇香积寺村","陕西省西安市长安区郭杜镇香积寺村","AREA-101270109",null,null],["1171733600224149506","香云寺","佛教","汉语系","陕西省","西安市","蓝田县","陕西省西安市蓝田县汤峪镇上峙峪村","陕西省西安市蓝田县汤峪镇上峙峪村","AREA-101270110",null,null],["1171733600131874819","新兴寺","佛教","汉语系","陕西省","西安市","户县","陕西省西安市户县石井镇直峪口村","陕西省西安市户县石井镇直峪口村","AREA-101270112",null,null],["1171733599079104518","兴国寺","佛教","汉语系","陕西省","西安市","长安区","陕西省西安市长安区兴隆乡西甘河","陕西省西安市长安区兴隆乡西甘河","AREA-101270109",null,null],["1171733599083298823","兴教寺","佛教","汉语系","陕西省","西安市","长安区","陕西省西安市长安区杜曲镇西韦村","陕西省西安市长安区杜曲镇西韦村","AREA-101270109",null,null],["1171733599079104519","兴庆寺","佛教","汉语系","陕西省","西安市","长安区","陕西省西安市长安区引镇街道嘉午台","陕西省西安市长安区引镇街道嘉午台","AREA-101270109",null,null],["1171733601222393867","兴泉寺","佛教","汉语系","陕西省","西安市","周至县","陕西省西安市周至县二曲镇渭泉村","陕西省西安市周至县二曲镇渭泉村","AREA-101270111",null,null],["1171733599586615302","延福寺","佛教","汉语系","陕西省","西安市","长安区","陕西省西安市长安区滦镇街道白石峪村","陕西省西安市长安区滦镇街道白石峪村","AREA-101270109",null,null],["1171733600480002048","阎良观音寺","佛教","汉语系","陕西省","西安市","阎良区","陕西省西安市阎良区关山镇康桥东丁村","陕西省西安市阎良区关山镇康桥东丁村","AREA-101270107",null,null],["1171733601222393860","涌泉寺","佛教","汉语系","陕西省","西安市","周至县","陕西省西安市周至县马召镇涌泉村","陕西省西安市周至县马召镇涌泉村","AREA-101270111",null,null],["1171733599754387458","元音禅寺","佛教","汉语系","陕西省","西安市","长安区","陕西省西安市长安区终南山新贯寺","陕西省西安市长安区终南山新贯寺","AREA-101270109",null,null],["1171733599083298822","圆觉寺","佛教","汉语系","陕西省","西安市","长安区","陕西省西安市长安区兴隆街道西甘河","陕西省西安市长安区兴隆街道西甘河","AREA-101270109",null,null],["1171733601222393856","圆觉寺","佛教","汉语系","陕西省","西安市","周至县","陕西省西安市周至县马召镇枣林村","陕西省西安市周至县马召镇枣林村","AREA-101270111",null,null],["1171733600140263428","圆胜寺","佛教","汉语系","陕西省","西安市","户县","陕西省西安市户县草堂镇宋东村","陕西省西安市户县草堂镇宋东村","AREA-101270112",null,null],["1171733600140263425","圆通寺","佛教","汉语系","陕西省","西安市","户县","陕西省西安市户县石井镇仝夏村","陕西省西安市户县石井镇仝夏村","AREA-101270112",null,null],["1171733600140263429","云际寺","佛教","汉语系","陕西省","西安市","户县","陕西省西安市户县庞光镇西焦蒋村","陕西省西安市户县庞光镇西焦蒋村","AREA-101270112",null,null],["1171733600308035584","云居寺西五台后台","佛教","汉语系","陕西省","西安市","莲湖区","陕西省西安市莲湖区香米园北巷27号","陕西省西安市莲湖区香米园北巷27号","AREA-101270103",null,null],["1171733600224149507","云居寺西五台前台","佛教","汉语系","陕西省","西安市","莲湖区","陕西省西安莲湖区洒金桥162号","陕西省西安莲湖区洒金桥162号","AREA-101270103",null,null],["1171733600136069123","云溪寺","佛教","汉语系","陕西省","西安市","户县","陕西省西安市户县玉蝉镇陂头村","陕西省西安市户县玉蝉镇陂头村","AREA-101270112",null,null],["1171733599586615297","至相寺","佛教","汉语系","陕西省","西安市","长安区","陕西省西安市长安区子午街道天子峪","陕西省西安市长安区子午街道天子峪","AREA-101270109",null,null],["1171733601222393865","终南山茅蓬禅寺","佛教","汉语系","陕西省","西安市","周至县","陕西省西安市周至县九峰镇耿峪村","陕西省西安市周至县九峰镇耿峪村","AREA-101270111",null,null],["1171733600874266624","竹林寺","佛教","汉语系","陕西省","西安市","周至县","陕西省西安市周至县司竹镇南司竹村","陕西省西安市周至县司竹镇南司竹村","AREA-101270111",null,null],["1171733600140263436","庄严寺","佛教","汉语系","陕西省","西安市","户县","陕西省西安市户县秦渡镇枣林寨村","陕西省西安市户县秦渡镇枣林寨村","AREA-101270112",null,null],["1171733599418843136","紫竹林寺","佛教","汉语系","陕西省","西安市","长安区","陕西省西安市长安区五台乡南五台","陕西省西安市长安区五台乡南五台","AREA-101270109",null,null]]}