{"key":"city-0337-新疆维吾尔自治区-博尔塔拉蒙古自治州","province":"新疆维吾尔自治区","city":"博尔塔拉蒙古自治州","count":3,"fields":["id","name","religion","faction","province","city","county","address","fullAddress","regionCode","latitude","longitude"],"places":[["1171733950863769600","白庙","佛教","藏语系","新疆维吾尔自治区","博尔塔拉蒙古自治州","精河县","新疆维吾尔自治区博尔塔拉蒙古自治州精河县托里乡乌拉斯台村白庙","新疆维吾尔自治区博尔塔拉蒙古自治州精河县托里乡乌拉斯台村白庙","AREA-101310602",null,null],["1171733950784077824","克西克特查干苏木","佛教","藏语系","新疆维吾尔自治区","博尔塔拉蒙古自治州","温泉县","新疆维吾尔自治区博尔塔拉蒙古自治州温泉县查干屯格乡查干苏木村克西克特查干苏木","新疆维吾尔自治区博尔塔拉蒙古自治州温泉县查干屯格乡查干苏木村克西克特查干苏木","AREA-101310603",null,null],["1171733950695997440","图布新特苏木","佛教","藏语系","新疆维吾尔自治区","博尔塔拉蒙古自治州","博乐市","新疆维吾尔自治区博尔塔拉蒙古自治州博乐市五一水库东侧图布新特苏木","新疆维吾尔自治区博尔塔拉蒙古自治州博乐市五一水库东侧图布新特苏木","AREA-101310601",null,null]]}