{"key":"city-0140-黑龙江省-七台河市","province":"黑龙江省","city":"七台河市","count":3,"fields":["id","name","religion","faction","province","city","county","address","fullAddress","regionCode","latitude","longitude"],"places":[["1171734030803009537","佛宝寺","佛教","汉语系","黑龙江省","七台河市","茄子河区","黑龙江省七台河市茄子河区东胜村","黑龙江省七台河市茄子河区东胜村","AREA-101080903",null,null],["1171734030719123456","极灵寺","佛教","汉语系","黑龙江省","七台河市","勃利县","黑龙江省七台河市勃利县大四站镇吉兴河水库","黑龙江省七台河市勃利县大四站镇吉兴河水库","AREA-101080904",null,null],["1171734030803009536","静修寺","佛教","汉语系","黑龙江省","七台河市","勃利县","黑龙江省七台河市勃利县杏树朝鲜乡杏树村","黑龙江省七台河市勃利县杏树朝鲜乡杏树村","AREA-101080904",null,null]]}