{"key":"city-0078-广西壮族自治区-南宁市","province":"广西壮族自治区","city":"南宁市","count":14,"fields":["id","name","religion","faction","province","city","county","address","fullAddress","regionCode","latitude","longitude"],"places":[["1171733553591877634","宾阳县黎塘镇龙岩寺","佛教","汉语系","广西壮族自治区","南宁市","宾阳县","广西壮族自治区南宁市宾阳县黎塘公园内","广西壮族自治区南宁市宾阳县黎塘公园内","AREA-101200111",null,null],["1171733553759649793","广西佛教协会天宁寺","佛教","汉语系","广西壮族自治区","南宁市","江南区","广西壮族自治区南宁市友谊路78号","广西壮族自治区南宁市友谊路78号","AREA-101200103",null,null],["1171733553675763712","横县宝华山应天寿佛寺","佛教","汉语系","广西壮族自治区","南宁市","横县","广西壮族自治区南宁市横县那阳镇六旺村","广西壮族自治区南宁市横县那阳镇六旺村","AREA-101200112",null,null],["1171733553759649792","横县横州佛教活动点","佛教","汉语系","广西壮族自治区","南宁市","横县","广西壮族自治区南宁市横县横州镇江北路西二巷26－3号","广西壮族自治区南宁市横县横州镇江北路西二巷26－3号","AREA-101200112",null,null],["1171733554086805505","马山县佛教居士林","佛教","汉语系","广西壮族自治区","南宁市","马山县","广西壮族自治区南宁市马山县白山镇西华街451号","广西壮族自治区南宁市马山县白山镇西华街451号","AREA-101200109",null,null],["1171733553843535872","马山县古零镇灵阳寺","佛教","汉语系","广西壮族自治区","南宁市","马山县","广西壮族自治区南宁市马山县古零镇丹入屯","广西壮族自治区南宁市马山县古零镇丹入屯","AREA-101200109",null,null],["1171733554090999809","马山县古零镇弄拉普陀寺","佛教","汉语系","广西壮族自治区","南宁市","马山县","广西壮族自治区马山县古零镇","广西壮族自治区马山县古零镇","AREA-101200109",null,null],["1171733554090999808","马山县圆觉寺","佛教","汉语系","广西壮族自治区","南宁市","马山县","广西壮族自治区南宁市马山县白山镇内昂路西二巷龙港山","广西壮族自治区南宁市马山县白山镇内昂路西二巷龙港山","AREA-101200109",null,null],["1171733554090999810","南宁市观音禅寺","佛教","汉语系","广西壮族自治区","南宁市","青秀区","广西壮族自治区南宁市青秀区凤岭南路6号青秀山风景区内","广西壮族自治区南宁市青秀区凤岭南路6号青秀山风景区内","AREA-101200102",null,null],["1171733554170691584","南宁市水月庵","佛教","汉语系","广西壮族自治区","南宁市","青秀区","广西壮族自治区南宁市青秀区凤岭南路6号青秀山风景区内","广西壮族自治区南宁市青秀区凤岭南路6号青秀山风景区内","AREA-101200102",null,null],["1171733554254577664","上林县法性寺","佛教","汉语系","广西壮族自治区","南宁市","上林县","广西壮族自治区南宁市上林县大丰镇东春村","广西壮族自治区南宁市上林县大丰镇东春村","AREA-101200110",null,null],["1171733554254577666","上林县莲音寺","佛教","汉语系","广西壮族自治区","南宁市","上林县","广西壮族自治区南宁市上林县大丰镇木棉水库","广西壮族自治区南宁市上林县大丰镇木棉水库","AREA-101200110",null,null],["1171733554170691585","上林县三教寺","佛教","汉语系","广西壮族自治区","南宁市","上林县","广西壮族自治区南宁市上林县大丰镇正街","广西壮族自治区南宁市上林县大丰镇正街","AREA-101200110",null,null],["1171733554254577665","上林县三里镇观音阁","佛教","汉语系","广西壮族自治区","南宁市","上林县","广西壮族自治区南宁市上林县三里镇南街","广西壮族自治区南宁市上林县三里镇南街","AREA-101200110",null,null]]}